gsheetsplus/__init__.py
gsheetsplus/api.py
gsheetsplus/gsheetsplus.py
gsheetsplus-0.3.5.dist-info/LICENSE
gsheetsplus-0.3.5.dist-info/METADATA
gsheetsplus-0.3.5.dist-info/WHEEL
gsheetsplus-0.3.5.dist-info/top_level.txt
gsheetsplus-0.3.5.dist-info/RECORD
