Metadata-Version: 2.1
Name: gsheetsplus
Version: 0.3.5
Summary: Extending Gsheets for added functionalities
Home-page: https://github.com/tanmaypandey7/gsheetsplus
Author: Tanmay Pandey
Author-email: tanmaypandey1998@gmail.com
License: MIT
Platform: UNKNOWN
Classifier: License :: OSI Approved :: MIT License
Classifier: Programming Language :: Python :: 3.8
Requires-Dist: gsheets
Requires-Dist: matplotlib
